gpubench/__init__.py
gpubench/main.py
gpubench-1.0.0.dist-info/METADATA
gpubench-1.0.0.dist-info/WHEEL
gpubench-1.0.0.dist-info/entry_points.txt
gpubench-1.0.0.dist-info/licenses/LICENSE
gpubench-1.0.0.dist-info/RECORD
