Metadata-Version: 2.1
Name: gpubench
Version: 1.0.0
Summary: A tool for reporting GPU benchmark results and information
Project-URL: Homepage, https://github.com/maokangkun/gpu-test
Project-URL: Bug Tracker, https://github.com/maokangkun/gpu-test/issues
Author-email: Kangkun Mao <maokangkun@pjlab.org.cn>
License-File: LICENSE
Classifier: License :: OSI Approved :: MIT License
Classifier: Operating System :: OS Independent
Classifier: Programming Language :: Python :: 3
Requires-Python: >=3.9
Requires-Dist: nvidia-ml-py
Requires-Dist: psutil
Requires-Dist: torch
Requires-Dist: torchvision
Requires-Dist: transformers
